numba_dpex/__init__.py
numba_dpex/_version.py
numba_dpex/register_kernel_api_overloads.py
numba_dpex/core/__init__.py
numba_dpex/core/config.py
numba_dpex/core/debuginfo.py
numba_dpex/core/decorators.py
numba_dpex/core/descriptor.py
numba_dpex/core/dpjit_dispatcher.py
numba_dpex/core/exceptions.py
numba_dpex/core/kernel_launcher.py
numba_dpex/core/lowering.py
numba_dpex/core/boxing/__init__.py
numba_dpex/core/boxing/ranges.py
numba_dpex/core/boxing/usm_ndarray.py
numba_dpex/core/datamodel/__init__.py
numba_dpex/core/datamodel/models.py
numba_dpex/core/overloads/__init__.py
numba_dpex/core/overloads/ranges_overloads.py
numba_dpex/core/parfors/__init__.py
numba_dpex/core/parfors/kernel_builder.py
numba_dpex/core/parfors/parfor_diagnostics.py
numba_dpex/core/parfors/parfor_lowerer.py
numba_dpex/core/parfors/parfor_pass.py
numba_dpex/core/parfors/parfor_sentinel_replace_pass.py
numba_dpex/core/parfors/reduction_helper.py
numba_dpex/core/parfors/reduction_kernel_builder.py
numba_dpex/core/parfors/kernel_templates/__init__.py
numba_dpex/core/parfors/kernel_templates/kernel_template_iface.py
numba_dpex/core/parfors/kernel_templates/range_kernel_template.py
numba_dpex/core/parfors/kernel_templates/reduction_template.py
numba_dpex/core/passes/__init__.py
numba_dpex/core/passes/dufunc_inliner.py
numba_dpex/core/passes/parfor_legalize_cfd_pass.py
numba_dpex/core/passes/passes.py
numba_dpex/core/pipelines/__init__.py
numba_dpex/core/pipelines/dpjit_compiler.py
numba_dpex/core/pipelines/kernel_compiler.py
numba_dpex/core/runtime/__init__.py
numba_dpex/core/runtime/_dpexrt_python.pyd
numba_dpex/core/runtime/context.py
numba_dpex/core/targets/__init__.py
numba_dpex/core/targets/dpjit_target.py
numba_dpex/core/types/__init__.py
numba_dpex/core/types/dpctl_types.py
numba_dpex/core/types/dpnp_ndarray_type.py
numba_dpex/core/types/kernel_dispatcher_type.py
numba_dpex/core/types/numba_types_short_names.py
numba_dpex/core/types/usm_ndarray_type.py
numba_dpex-0.23.0.dist-info/LICENSE
numba_dpex-0.23.0.dist-info/LICENSES.third-party
numba_dpex-0.23.0.dist-info/METADATA
numba_dpex-0.23.0.dist-info/WHEEL
numba_dpex-0.23.0.dist-info/top_level.txt
numba_dpex-0.23.0.dist-info/RECORD
