Metadata-Version: 2.1
Name: numba-dpex
Version: 0.23.0
Summary: An extension for Numba to add data-parallel offload capability
Home-page: https://github.com/IntelPython/numba-dpex
Author: Intel Corporation
License: Apache 2.0
Project-URL: Changelog, https://github.com/IntelPython/numba-dpex/blob/main/CHANGELOG.md
Project-URL: Documentation, https://intelpython.github.io/numba-dpex/
Project-URL: Homepage, https://github.com/IntelPython/numba-dpex
Project-URL: Issues, https://github.com/IntelPython/numba-dpex/issues
Project-URL: Repository, https://github.com/IntelPython/numba-dpex.git
Keywords: sycl,python3,numba,numpy,intel,mkl,oneapi,gpu,dpcpp
Platform: UNKNOWN
Classifier: Development Status :: 4 - Beta
Classifier: Environment :: GPU
Classifier: Environment :: Plugins
Classifier: Intended Audience :: Developers
Classifier: License :: OSI Approved :: Apache Software License
Classifier: Operating System :: OS Independent
Classifier: Programming Language :: Python :: 3
Classifier: Programming Language :: Python :: Implementation :: CPython
Classifier: Topic :: Software Development :: Compilers
Classifier: Operating System :: Microsoft :: Windows
Classifier: Operating System :: POSIX :: Linux
Requires-Python: >=3.9
License-File: LICENSE
License-File: LICENSES.third-party
Requires-Dist: numba >=0.59.0
Requires-Dist: llvmlite >=0.42.0
Requires-Dist: dpctl >=0.16.1
Requires-Dist: dpnp >=0.14.0
Requires-Dist: numpy >=1.24.0
Requires-Dist: dpcpp-llvm-spirv >=2024.1
Requires-Dist: dpcpp-cpp-rt
Requires-Dist: intel-cmplr-lib-rt
